Metadata-Version: 2.4
Name: seed-autogen
Version: 0.1.21
Summary: A programming framework for agentic AI
Project-URL: Homepage, https://ag2.ai/
Project-URL: Documentation, https://docs.ag2.ai/docs/Home
Project-URL: Tracker, https://github.com/ag2ai/ag2/issues
Project-URL: Source, https://github.com/ag2ai/ag2
Project-URL: Discord, https://discord.gg/pAbnFJrkgZ
Author-email: Chi Wang <support@ag2.ai>, Qingyun Wu <support@ag2.ai>
License: Apache Software License 2.0
License-File: LICENSE
License-File: NOTICE.md
Keywords: ag2,ag2.ai,ag2ai,agent,agentic,ai,autogen,pyautogen
Classifier: Development Status :: 5 - Production/Stable
Classifier: Intended Audience :: Developers
Classifier: Intended Audience :: Information Technology
Classifier: License :: OSI Approved :: Apache Software License
Classifier: Operating System :: OS Independent
Classifier: Programming Language :: Python
Classifier: Programming Language :: Python :: 3
Classifier: Programming Language :: Python :: 3 :: Only
Classifier: Programming Language :: Python :: 3.9
Classifier: Programming Language :: Python :: 3.10
Classifier: Programming Language :: Python :: 3.11
Classifier: Programming Language :: Python :: 3.12
Classifier: Programming Language :: Python :: 3.13
Classifier: Programming Language :: Python :: Implementation :: CPython
Classifier: Topic :: Software Development
Classifier: Topic :: Software Development :: Libraries
Classifier: Topic :: Software Development :: Libraries :: Application Frameworks
Classifier: Topic :: Software Development :: Libraries :: Python Modules
Requires-Python: <3.14,>=3.9
Requires-Dist: asyncer==0.0.8
Requires-Dist: diskcache
Requires-Dist: docker
Requires-Dist: fast-depends<3,>=2.4.12
Requires-Dist: flaml
Requires-Dist: numpy<2.0.0,>=1.24.0; python_version < '3.13'
Requires-Dist: numpy>=2.1; python_version >= '3.13'
Requires-Dist: openai>=1.58
Requires-Dist: packaging
Requires-Dist: pydantic!=2.6.0,<3,>=1.10
Requires-Dist: python-dotenv
Requires-Dist: termcolor
Requires-Dist: tiktoken
Requires-Dist: websockets<15,>=14
Provides-Extra: anthropic
Requires-Dist: anthropic[vertex]>=0.23.1; extra == 'anthropic'
Provides-Extra: autobuild
Requires-Dist: chromadb; extra == 'autobuild'
Requires-Dist: huggingface-hub; extra == 'autobuild'
Requires-Dist: pysqlite3-binary; extra == 'autobuild'
Requires-Dist: sentence-transformers; extra == 'autobuild'
Provides-Extra: bedrock
Requires-Dist: boto3>=1.34.149; extra == 'bedrock'
Provides-Extra: blendsearch
Requires-Dist: flaml[blendsearch]; extra == 'blendsearch'
Provides-Extra: captainagent
Requires-Dist: pandas; extra == 'captainagent'
Requires-Dist: pyautogen[autobuild]; extra == 'captainagent'
Provides-Extra: cerebras
Requires-Dist: cerebras-cloud-sdk>=1.0.0; extra == 'cerebras'
Provides-Extra: cohere
Requires-Dist: cohere>=5.5.8; extra == 'cohere'
Provides-Extra: cosmosdb
Requires-Dist: azure-cosmos>=4.2.0; extra == 'cosmosdb'
Provides-Extra: gemini
Requires-Dist: google-auth; extra == 'gemini'
Requires-Dist: google-cloud-aiplatform; extra == 'gemini'
Requires-Dist: google-generativeai<1,>=0.5; extra == 'gemini'
Requires-Dist: jsonschema; extra == 'gemini'
Requires-Dist: pillow; extra == 'gemini'
Requires-Dist: pydantic; extra == 'gemini'
Provides-Extra: graph
Requires-Dist: matplotlib; extra == 'graph'
Requires-Dist: networkx; extra == 'graph'
Provides-Extra: graph-rag-falkor-db
Requires-Dist: falkordb>=1.0.10; extra == 'graph-rag-falkor-db'
Requires-Dist: graphrag-sdk==0.3.3; extra == 'graph-rag-falkor-db'
Provides-Extra: groq
Requires-Dist: groq>=0.9.0; extra == 'groq'
Provides-Extra: interop
Requires-Dist: pyautogen[interop-crewai,interop-langchain,interop-pydantic-ai]; extra == 'interop'
Provides-Extra: interop-crewai
Requires-Dist: crewai[tools]<1,>=0.86; (python_version >= '3.10' and python_version < '3.13') and extra == 'interop-crewai'
Requires-Dist: weaviate-client==4.10.2; (python_version >= '3.10' and python_version < '3.13') and extra == 'interop-crewai'
Provides-Extra: interop-langchain
Requires-Dist: langchain-community<1,>=0.3.12; extra == 'interop-langchain'
Provides-Extra: interop-pydantic-ai
Requires-Dist: pydantic-ai==0.0.13; extra == 'interop-pydantic-ai'
Provides-Extra: jupyter-executor
Requires-Dist: ipykernel>=6.29.0; extra == 'jupyter-executor'
Requires-Dist: jupyter-client>=8.6.0; extra == 'jupyter-executor'
Requires-Dist: jupyter-kernel-gateway; extra == 'jupyter-executor'
Requires-Dist: requests; extra == 'jupyter-executor'
Requires-Dist: websocket-client; extra == 'jupyter-executor'
Provides-Extra: lmm
Requires-Dist: pillow; extra == 'lmm'
Requires-Dist: replicate; extra == 'lmm'
Provides-Extra: long-context
Requires-Dist: llmlingua<0.3; extra == 'long-context'
Provides-Extra: mathchat
Requires-Dist: pydantic==1.10.9; extra == 'mathchat'
Requires-Dist: sympy; extra == 'mathchat'
Requires-Dist: wolframalpha; extra == 'mathchat'
Provides-Extra: mistral
Requires-Dist: mistralai>=1.0.1; extra == 'mistral'
Provides-Extra: neo4j
Requires-Dist: docx2txt==0.8; extra == 'neo4j'
Requires-Dist: llama-index-core==0.12.5; extra == 'neo4j'
Requires-Dist: llama-index-graph-stores-neo4j==0.4.2; extra == 'neo4j'
Requires-Dist: llama-index-readers-web==0.3.3; extra == 'neo4j'
Requires-Dist: llama-index==0.12.5; extra == 'neo4j'
Provides-Extra: ollama
Requires-Dist: fix-busted-json>=0.0.18; extra == 'ollama'
Requires-Dist: ollama>=0.3.3; extra == 'ollama'
Provides-Extra: redis
Requires-Dist: redis; extra == 'redis'
Provides-Extra: retrievechat
Requires-Dist: beautifulsoup4; extra == 'retrievechat'
Requires-Dist: chromadb==0.5.3; extra == 'retrievechat'
Requires-Dist: ipython; extra == 'retrievechat'
Requires-Dist: markdownify; extra == 'retrievechat'
Requires-Dist: protobuf==4.25.3; extra == 'retrievechat'
Requires-Dist: pypdf; extra == 'retrievechat'
Requires-Dist: sentence-transformers; extra == 'retrievechat'
Provides-Extra: retrievechat-mongodb
Requires-Dist: pyautogen[retrievechat]; extra == 'retrievechat-mongodb'
Requires-Dist: pymongo>=4.0.0; extra == 'retrievechat-mongodb'
Provides-Extra: retrievechat-pgvector
Requires-Dist: pgvector>=0.2.5; extra == 'retrievechat-pgvector'
Requires-Dist: psycopg>=3.1.18; (platform_system == 'Linux') and extra == 'retrievechat-pgvector'
Requires-Dist: psycopg[binary]>=3.1.18; (platform_system == 'Windows' or platform_system == 'Darwin') and extra == 'retrievechat-pgvector'
Requires-Dist: pyautogen[retrievechat]; extra == 'retrievechat-pgvector'
Provides-Extra: retrievechat-qdrant
Requires-Dist: fastembed>=0.3.1; extra == 'retrievechat-qdrant'
Requires-Dist: pyautogen[retrievechat]; extra == 'retrievechat-qdrant'
Requires-Dist: qdrant-client; extra == 'retrievechat-qdrant'
Provides-Extra: teachable
Requires-Dist: chromadb; extra == 'teachable'
Provides-Extra: test
Requires-Dist: fastapi<1,>=0.115.0; extra == 'test'
Requires-Dist: ipykernel; extra == 'test'
Requires-Dist: nbconvert; extra == 'test'
Requires-Dist: nbformat; extra == 'test'
Requires-Dist: pandas; extra == 'test'
Requires-Dist: pre-commit; extra == 'test'
Requires-Dist: pytest-asyncio; extra == 'test'
Requires-Dist: pytest-cov>=5; extra == 'test'
Requires-Dist: pytest<9,>=8; extra == 'test'
Provides-Extra: together
Requires-Dist: together>=1.2; extra == 'together'
Provides-Extra: twilio
Requires-Dist: fastapi<1,>=0.115.0; extra == 'twilio'
Requires-Dist: twilio>=9.3.2; extra == 'twilio'
Requires-Dist: uvicorn<1,>=0.30.6; extra == 'twilio'
Provides-Extra: types
Requires-Dist: mypy==1.9.0; extra == 'types'
Requires-Dist: pyautogen[interop,jupyter-executor,test]; extra == 'types'
Provides-Extra: websockets
Requires-Dist: websockets<15,>=14.0; extra == 'websockets'
Provides-Extra: websurfer
Requires-Dist: beautifulsoup4; extra == 'websurfer'
Requires-Dist: markdownify; extra == 'websurfer'
Requires-Dist: pathvalidate; extra == 'websurfer'
Requires-Dist: pdfminer-six; extra == 'websurfer'
